{
    "T*_units": "[K]",
    "M*_units": "[Solar mass]",
    "R*_units": "[Solar radius]",
    "FEH*_units": "[Fe/H]",
    "LOGG*_units": "log10[cm.s-2]",
    "T*": 5000.0,
    "T*_uperr": 100.0,
    "T*_lowerr": -100.0,
    "M*": 0.87,
    "M*_uperr": 0.03,
    "M*_lowerr": -0.03,
    "R*": 0.79,
    "R*_uperr": 0.02,
    "R*_lowerr": -0.02,
    "FEH*": 0.03,
    "FEH*_uperr": 0.12,
    "FEH*_lowerr": -0.12,
    "LOGG*": 4.58,
    "LOGG*_uperr": 0.01,
    "LOGG*_lowerr": -0.01,
    "S.Reference": "<a refstr=HEBRARD_ET_AL__2013 href=https://ui.adsabs.harvard.edu/abs/2013A%26A...549A.134H/abstract target=ref> Hebrard et al. 2013 </a>",
    "planets": [
        "b"
    ],
    "b": {
        "period_units": "[days]",
        "sma_units": "[AU]",
        "ecc_units": "",
        "inc_units": "[degree]",
        "omega_units": "[degree]",
        "mass_units": "[Jupiter mass]",
        "rp_units": "[Jupiter radius]",
        "t0_units": "[Julian Day]",
        "period": 1.7497798,
        "period_uperr": 1.2e-06,
        "period_lowerr": -1.2e-06,
        "sma": 0.0272,
        "sma_lowerr": 0.0003,
        "sma_uperr": -0.0003,
        "ars": 7.3801,
        "ars_lowerr": 0.1106,
        "ars_upper": -0.1073,
        "ecc": 0.0,
        "ecc_uperr": NaN,
        "ecc_lowerr": NaN,
        "inc": 85.35,
        "inc_uperr": 0.2,
        "inc_lowerr": -0.2,
        "mass": 0.46,
        "mass_uperr": 0.02,
        "mass_lowerr": -0.02,
        "rp": 1.27,
        "rp_uperr": 0.03,
        "rp_lowerr": -0.03,
        "t0": 2455793.68143,
        "t0_uperr": 9e-05,
        "t0_lowerr": -9e-05,
        "omega": 0.0,
        "omega_uperr": NaN,
        "omega_lowerr": NaN,
        "P.Reference": "<a refstr=HEBRARD_ET_AL__2013 href=https://ui.adsabs.harvard.edu/abs/2013A%26A...549A.134H/abstract target=ref> Hebrard et al. 2013 </a>"
    }
}